ros_test_msgs-2.3.0.data/data/include/test_msgs/test_msgs/message_fixtures.hpp
ros_test_msgs-2.3.0.data/data/include/test_msgs/test_msgs/service_fixtures.hpp
ros_test_msgs-2.3.0.data/data/include/test_msgs/test_msgs/action/fibonacci.h
ros_test_msgs-2.3.0.data/data/include/test_msgs/test_msgs/action/fibonacci.hpp
ros_test_msgs-2.3.0.data/data/include/test_msgs/test_msgs/action/nested_message.h
ros_test_msgs-2.3.0.data/data/include/test_msgs/test_msgs/action/nested_message.hpp
ros_test_msgs-2.3.0.data/data/include/test_msgs/test_msgs/action/detail/fibonacci__builder.hpp
ros_test_msgs-2.3.0.data/data/include/test_msgs/test_msgs/action/detail/fibonacci__description.c
ros_test_msgs-2.3.0.data/data/include/test_msgs/test_msgs/action/detail/fibonacci__functions.c
ros_test_msgs-2.3.0.data/data/include/test_msgs/test_msgs/action/detail/fibonacci__functions.h
ros_test_msgs-2.3.0.data/data/include/test_msgs/test_msgs/action/detail/fibonacci__rosidl_typesupport_fastrtps_c.h
ros_test_msgs-2.3.0.data/data/include/test_msgs/test_msgs/action/detail/fibonacci__rosidl_typesupport_fastrtps_cpp.hpp
ros_test_msgs-2.3.0.data/data/include/test_msgs/test_msgs/action/detail/fibonacci__rosidl_typesupport_introspection_c.h
ros_test_msgs-2.3.0.data/data/include/test_msgs/test_msgs/action/detail/fibonacci__rosidl_typesupport_introspection_cpp.hpp
ros_test_msgs-2.3.0.data/data/include/test_msgs/test_msgs/action/detail/fibonacci__struct.h
ros_test_msgs-2.3.0.data/data/include/test_msgs/test_msgs/action/detail/fibonacci__struct.hpp
ros_test_msgs-2.3.0.data/data/include/test_msgs/test_msgs/action/detail/fibonacci__traits.hpp
ros_test_msgs-2.3.0.data/data/include/test_msgs/test_msgs/action/detail/fibonacci__type_support.c
ros_test_msgs-2.3.0.data/data/include/test_msgs/test_msgs/action/detail/fibonacci__type_support.cpp
ros_test_msgs-2.3.0.data/data/include/test_msgs/test_msgs/action/detail/fibonacci__type_support.h
ros_test_msgs-2.3.0.data/data/lib/python3.10/site-packages/test_msgs-2.3.0-py3.10.egg-info/PKG-INFO
ros_test_msgs-2.3.0.data/data/lib/python3.10/site-packages/test_msgs-2.3.0-py3.10.egg-info/SOURCES.txt
ros_test_msgs-2.3.0.data/data/lib/python3.10/site-packages/test_msgs-2.3.0-py3.10.egg-info/dependency_links.txt
ros_test_msgs-2.3.0.data/data/lib/python3.10/site-packages/test_msgs-2.3.0-py3.10.egg-info/top_level.txt
ros_test_msgs-2.3.0.dist-info/METADATA
ros_test_msgs-2.3.0.dist-info/WHEEL
ros_test_msgs-2.3.0.dist-info/top_level.txt
ros_test_msgs-2.3.0.dist-info/RECORD
