Metadata-Version: 2.4
Name: ros-test-msgs
Version: 2.3.0
Summary: Wheel for the test_msgs (ros-test-msgs) ROS 2 package.
Requires-Dist: ros-rosidl-default-runtime~=1.7.1
Requires-Dist: ros-builtin-interfaces~=2.3.0
Dynamic: description
Dynamic: description-content-type
Dynamic: requires-dist
Dynamic: summary
